clx/__init__.py
clx/xms/__about__.py
clx/xms/__init__.py
clx/xms/api.py
clx/xms/client.py
clx/xms/deserialize.py
clx/xms/exceptions.py
clx/xms/serialize.py
clx_sdk_xms-1.0.0.dist-info/DESCRIPTION.rst
clx_sdk_xms-1.0.0.dist-info/LICENSE.txt
clx_sdk_xms-1.0.0.dist-info/METADATA
clx_sdk_xms-1.0.0.dist-info/RECORD
clx_sdk_xms-1.0.0.dist-info/WHEEL
clx_sdk_xms-1.0.0.dist-info/metadata.json
clx_sdk_xms-1.0.0.dist-info/top_level.txt
