Metadata-Version: 1.1
Name: clx-sdk-xms
Version: 1.0.0
Summary: Library for CLX Communications HTTP REST Messaging API
Home-page: https://github.com/clxcommunications/sdk-xms-python
Author: Robert Helgesson
Author-email: robert@chaitsa.com
License: Apache License, Version 2.0
Keywords: messaging mobile sms
Platform: UNKNOWN
Classifier: Development Status :: 5 - Production/Stable
Classifier: Intended Audience :: Developers
Classifier: Intended Audience :: Telecommunications Industry
Classifier: License :: OSI Approved :: Apache Software License
Classifier: Programming Language :: Python :: 2
Classifier: Programming Language :: Python :: 2.7
Classifier: Programming Language :: Python :: 3
Classifier: Programming Language :: Python :: 3.3
Classifier: Programming Language :: Python :: 3.4
Classifier: Programming Language :: Python :: 3.5
Classifier: Programming Language :: Python :: 3.6
Classifier: Topic :: Communications :: Telephony
Classifier: Topic :: Communications
